<!DOCTYPE ui:UiBinder SYSTEM "http://dl.google.com/gwt/DTD/xhtml.ent">

<ui:UiBinder xmlns:ui='urn:ui:com.google.gwt.uibinder'
	xmlns:g='urn:import:com.google.gwt.user.client.ui'
	xmlns:pf='urn:import:com.fave100.client.pagefragments.footer'
	xmlns:w='urn:import:com.fave100.client.widgets'
	ui:generateFormat='com.google.gwt.i18n.rebind.format.PropertiesFormat'
	ui:generateKeys='com.google.gwt.i18n.rebind.keygen.MD5KeyGenerator'
	ui:generateLocales='default'>

	<g:HTMLPanel ui:styleName="container">
		<g:HTMLPanel ui:field="topBar"/>
		<div class="content">
			<g:Label ui:field="songTitle">Song Title</g:Label>
			<g:Label ui:field="artistName">Artist Name</g:Label>
			<g:Label ui:field="releaseDate">Release Date</g:Label>
			<g:Frame width="640px" height="360px" ui:styleName="youTubePlayer" ui:field="youTubePlayer"/>
			<w:WhylineWaterfall ui:field="whylineWaterfall"/>
		</div>	
		<pf:Footer/>
	</g:HTMLPanel>
</ui:UiBinder>
